hvc/__init__.py
hvc/embeddings.py
hvc/functional.py
hvc/memory.py
hvc/models.py
hvc/structures.py
hvc/types.py
hvc/utils.py
hvc/version.py
hvc/datasets/__init__.py
hvc/datasets/abalone.py
hvc/datasets/acute_inflammation.py
hvc/datasets/acute_nephritis.py
hvc/datasets/adult.py
hvc/datasets/airfoil_self_noise.py
hvc/datasets/annealing.py
hvc/datasets/arrhythmia.py
hvc/datasets/audiology_std.py
hvc/datasets/balance_scale.py
hvc/datasets/balloons.py
hvc/datasets/bank.py
hvc/datasets/beijing_air_quality.py
hvc/datasets/blood.py
hvc/datasets/breast_cancer.py
hvc/datasets/breast_cancer_wisc.py
hvc/datasets/breast_cancer_wisc_diag.py
hvc/datasets/breast_cancer_wisc_prog.py
hvc/datasets/breast_tissue.py
hvc/datasets/car.py
hvc/datasets/cardiotocography_10clases.py
hvc/datasets/cardiotocography_3clases.py
hvc/datasets/ccpp.py
hvc/datasets/chess_krvk.py
hvc/datasets/chess_krvkp.py
hvc/datasets/congressional_voting.py
hvc/datasets/conn_bench_sonar_mines_rocks.py
hvc/datasets/conn_bench_vowel_deterding.py
hvc/datasets/connect_4.py
hvc/datasets/contrac.py
hvc/datasets/credit_approval.py
hvc/datasets/cylinder_bands.py
hvc/datasets/dataset.py
hvc/datasets/dermatology.py
hvc/datasets/echocardiogram.py
hvc/datasets/ecoli.py
hvc/datasets/emg_hand_gestures.py
hvc/datasets/energy_y1.py
hvc/datasets/energy_y2.py
hvc/datasets/european_languages.py
hvc/datasets/fertility.py
hvc/datasets/flags.py
hvc/datasets/glass.py
hvc/datasets/haberman_survival.py
hvc/datasets/hayes_roth.py
hvc/datasets/heart_cleveland.py
hvc/datasets/heart_hungarian.py
hvc/datasets/heart_switzerland.py
hvc/datasets/heart_va.py
hvc/datasets/hepatitis.py
hvc/datasets/hill_valley.py
hvc/datasets/horse_colic.py
hvc/datasets/ilpd_indian_liver.py
hvc/datasets/image_segmentation.py
hvc/datasets/ionosphere.py
hvc/datasets/iris.py
hvc/datasets/isolet.py
hvc/datasets/led_display.py
hvc/datasets/lenses.py
hvc/datasets/letter.py
hvc/datasets/libras.py
hvc/datasets/low_res_spect.py
hvc/datasets/lung_cancer.py
hvc-0.1.0.dist-info/LICENSE
hvc-0.1.0.dist-info/METADATA
hvc-0.1.0.dist-info/WHEEL
hvc-0.1.0.dist-info/top_level.txt
hvc-0.1.0.dist-info/RECORD
